tkintertools/__init__.py
tkintertools/__main__.py
tkintertools/constants.py
tkintertools/tools_3d.py
tkintertools_dev-2.6.5.dist-info/LICENSE
tkintertools_dev-2.6.5.dist-info/METADATA
tkintertools_dev-2.6.5.dist-info/WHEEL
tkintertools_dev-2.6.5.dist-info/top_level.txt
tkintertools_dev-2.6.5.dist-info/RECORD
