Metadata-Version: 2.1
Name: tkintertools-dev
Version: 2.6.5
Summary: An auxiliary module of the tkinder module
Home-page: https://github.com/Xiaokang2022/tkintertools
Author: Xiaokang2022
Author-email: 2951256653@qq.com
License: MulanPSL-2.0
Keywords: tkinter,tkintertools,GUI
Classifier: Programming Language :: Python :: 3
Classifier: License :: OSI Approved :: Mulan Permissive Software License v2 (MulanPSL-2.0)
Classifier: Operating System :: OS Independent
Requires-Python: >=3.8
License-File: LICENSE
